[{"dlc":"mp_m_executive_01","component":7,"relative":0,"absolute":123,"texture":0,"palette":0},{"dlc":"mp_m_executive_01","component":7,"relative":0,"absolute":123,"texture":0,"palette":1},{"dlc":"mp_m_executive_01","component":7,"relative":0,"absolute":123,"texture":1,"palette":0},{"dlc":"mp_m_executive_01","component":7,"relative":0,"absolute":123,"texture":1,"palette":1},{"dlc":"mp_m_executive_01","component":7,"relative":1,"absolute":124,"texture":0,"palette":0},{"dlc":"mp_m_executive_01","component":7,"relative":1,"absolute":124,"texture":0,"palette":1},{"dlc":"mp_m_executive_01","component":7,"relative":1,"absolute":124,"texture":1,"palette":0},{"dlc":"mp_m_executive_01","component":7,"relative":1,"absolute":124,"texture":1,"palette":1}]