[{"dlc":"mp_f_stunt_01","component":11,"relative":0,"absolute":144,"texture":0,"palette":0},{"dlc":"mp_f_stunt_01","component":11,"relative":0,"absolute":144,"texture":0,"palette":1},{"dlc":"mp_f_stunt_01","component":11,"relative":0,"absolute":144,"texture":1,"palette":0},{"dlc":"mp_f_stunt_01","component":11,"relative":0,"absolute":144,"texture":1,"palette":1},{"dlc":"mp_f_stunt_01","component":11,"relative":0,"absolute":144,"texture":2,"palette":0},{"dlc":"mp_f_stunt_01","component":11,"relative":0,"absolute":144,"texture":2,"palette":1},{"dlc":"mp_f_stunt_01","component":11,"relative":0,"absolute":144,"texture":3,"palette":0},{"dlc":"mp_f_stunt_01","component":11,"relative":0,"absolute":144,"texture":3,"palette":1},{"dlc":"mp_f_stunt_01","component":11,"relative":0,"absolute":144,"texture":4,"palette":0},{"dlc":"mp_f_stunt_01","component":11,"relative":0,"absolute":144,"texture":4,"palette":1},{"dlc":"mp_f_stunt_01","component":11,"relative":0,"absolute":144,"texture":5,"palette":0},{"dlc":"mp_f_stunt_01","component":11,"relative":0,"absolute":144,"texture":5,"palette":1},{"dlc":"mp_f_stunt_01","component":11,"relative":0,"absolute":144,"texture":6,"palette":0},{"dlc":"mp_f_stunt_01","component":11,"relative":0,"absolute":144,"texture":6,"palette":1},{"dlc":"mp_f_stunt_01","component":11,"relative":0,"absolute":144,"texture":7,"palette":0},{"dlc":"mp_f_stunt_01","component":11,"relative":0,"absolute":144,"texture":7,"palette":1},{"dlc":"mp_f_stunt_01","component":11,"relative":0,"absolute":144,"texture":8,"palette":0},{"dlc":"mp_f_stunt_01","component":11,"relative":0,"absolute":144,"texture":8,"palette":1},{"dlc":"mp_f_stunt_01","component":11,"relative":0,"absolute":144,"texture":9,"palette":0},{"dlc":"mp_f_stunt_01","component":11,"relative":0,"absolute":144,"texture":9,"palette":1},{"dlc":"mp_f_stunt_01","component":11,"relative":1,"absolute":145,"texture":0,"palette":0},{"dlc":"mp_f_stunt_01","component":11,"relative":1,"absolute":145,"texture":0,"palette":1},{"dlc":"mp_f_stunt_01","component":11,"relative":1,"absolute":145,"texture":1,"palette":0},{"dlc":"mp_f_stunt_01","component":11,"relative":1,"absolute":145,"texture":1,"palette":1},{"dlc":"mp_f_stunt_01","component":11,"relative":1,"absolute":145,"texture":2,"palette":0},{"dlc":"mp_f_stunt_01","component":11,"relative":1,"absolute":145,"texture":2,"palette":1},{"dlc":"mp_f_stunt_01","component":11,"relative":1,"absolute":145,"texture":3,"palette":0},{"dlc":"mp_f_stunt_01","component":11,"relative":1,"absolute":145,"texture":3,"palette":1},{"dlc":"mp_f_stunt_01","component":11,"relative":1,"absolute":145,"texture":4,"palette":0},{"dlc":"mp_f_stunt_01","component":11,"relative":1,"absolute":145,"texture":4,"palette":1},{"dlc":"mp_f_stunt_01","component":11,"relative":1,"absolute":145,"texture":5,"palette":0},{"dlc":"mp_f_stunt_01","component":11,"relative":1,"absolute":145,"texture":5,"palette":1},{"dlc":"mp_f_stunt_01","component":11,"relative":1,"absolute":145,"texture":6,"palette":0},{"dlc":"mp_f_stunt_01","component":11,"relative":1,"absolute":145,"texture":6,"palette":1},{"dlc":"mp_f_stunt_01","component":11,"relative":1,"absolute":145,"texture":7,"palette":0},{"dlc":"mp_f_stunt_01","component":11,"relative":1,"absolute":145,"texture":7,"palette":1},{"dlc":"mp_f_stunt_01","component":11,"relative":1,"absolute":145,"texture":8,"palette":0},{"dlc":"mp_f_stunt_01","component":11,"relative":1,"absolute":145,"texture":8,"palette":1},{"dlc":"mp_f_stunt_01","component":11,"relative":1,"absolute":145,"texture":9,"palette":0},{"dlc":"mp_f_stunt_01","component":11,"relative":1,"absolute":145,"texture":9,"palette":1},{"dlc":"mp_f_stunt_01","component":11,"relative":1,"absolute":145,"texture":10,"palette":0},{"dlc":"mp_f_stunt_01","component":11,"relative":1,"absolute":145,"texture":10,"palette":1},{"dlc":"mp_f_stunt_01","component":11,"relative":1,"absolute":145,"texture":11,"palette":0},{"dlc":"mp_f_stunt_01","component":11,"relative":1,"absolute":145,"texture":11,"palette":1},{"dlc":"mp_f_stunt_01","component":11,"relative":2,"absolute":146,"texture":0,"palette":0},{"dlc":"mp_f_stunt_01","component":11,"relative":2,"absolute":146,"texture":0,"palette":1},{"dlc":"mp_f_stunt_01","component":11,"relative":2,"absolute":146,"texture":1,"palette":0},{"dlc":"mp_f_stunt_01","component":11,"relative":2,"absolute":146,"texture":1,"palette":1},{"dlc":"mp_f_stunt_01","component":11,"relative":2,"absolute":146,"texture":2,"palette":0},{"dlc":"mp_f_stunt_01","component":11,"relative":2,"absolute":146,"texture":2,"palette":1},{"dlc":"mp_f_stunt_01","component":11,"relative":2,"absolute":146,"texture":3,"palette":0},{"dlc":"mp_f_stunt_01","component":11,"relative":2,"absolute":146,"texture":3,"palette":1},{"dlc":"mp_f_stunt_01","component":11,"relative":2,"absolute":146,"texture":4,"palette":0},{"dlc":"mp_f_stunt_01","component":11,"relative":2,"absolute":146,"texture":4,"palette":1},{"dlc":"mp_f_stunt_01","component":11,"relative":2,"absolute":146,"texture":5,"palette":0},{"dlc":"mp_f_stunt_01","component":11,"relative":2,"absolute":146,"texture":5,"palette":1},{"dlc":"mp_f_stunt_01","component":11,"relative":2,"absolute":146,"texture":6,"palette":0},{"dlc":"mp_f_stunt_01","component":11,"relative":2,"absolute":146,"texture":6,"palette":1},{"dlc":"mp_f_stunt_01","component":11,"relative":2,"absolute":146,"texture":7,"palette":0},{"dlc":"mp_f_stunt_01","component":11,"relative":2,"absolute":146,"texture":7,"palette":1},{"dlc":"mp_f_stunt_01","component":11,"relative":2,"absolute":146,"texture":8,"palette":0},{"dlc":"mp_f_stunt_01","component":11,"relative":2,"absolute":146,"texture":8,"palette":1},{"dlc":"mp_f_stunt_01","component":11,"relative":2,"absolute":146,"texture":9,"palette":0},{"dlc":"mp_f_stunt_01","component":11,"relative":2,"absolute":146,"texture":9,"palette":1},{"dlc":"mp_f_stunt_01","component":11,"relative":3,"absolute":147,"texture":0,"palette":0},{"dlc":"mp_f_stunt_01","component":11,"relative":3,"absolute":147,"texture":0,"palette":1},{"dlc":"mp_f_stunt_01","component":11,"relative":3,"absolute":147,"texture":1,"palette":0},{"dlc":"mp_f_stunt_01","component":11,"relative":3,"absolute":147,"texture":1,"palette":1},{"dlc":"mp_f_stunt_01","component":11,"relative":3,"absolute":147,"texture":2,"palette":0},{"dlc":"mp_f_stunt_01","component":11,"relative":3,"absolute":147,"texture":2,"palette":1},{"dlc":"mp_f_stunt_01","component":11,"relative":3,"absolute":147,"texture":3,"palette":0},{"dlc":"mp_f_stunt_01","component":11,"relative":3,"absolute":147,"texture":3,"palette":1},{"dlc":"mp_f_stunt_01","component":11,"relative":3,"absolute":147,"texture":4,"palette":0},{"dlc":"mp_f_stunt_01","component":11,"relative":3,"absolute":147,"texture":4,"palette":1},{"dlc":"mp_f_stunt_01","component":11,"relative":3,"absolute":147,"texture":5,"palette":0},{"dlc":"mp_f_stunt_01","component":11,"relative":3,"absolute":147,"texture":5,"palette":1},{"dlc":"mp_f_stunt_01","component":11,"relative":3,"absolute":147,"texture":6,"palette":0},{"dlc":"mp_f_stunt_01","component":11,"relative":3,"absolute":147,"texture":6,"palette":1},{"dlc":"mp_f_stunt_01","component":11,"relative":3,"absolute":147,"texture":7,"palette":0},{"dlc":"mp_f_stunt_01","component":11,"relative":3,"absolute":147,"texture":7,"palette":1},{"dlc":"mp_f_stunt_01","component":11,"relative":3,"absolute":147,"texture":8,"palette":0},{"dlc":"mp_f_stunt_01","component":11,"relative":3,"absolute":147,"texture":8,"palette":1},{"dlc":"mp_f_stunt_01","component":11,"relative":3,"absolute":147,"texture":9,"palette":0},{"dlc":"mp_f_stunt_01","component":11,"relative":3,"absolute":147,"texture":9,"palette":1},{"dlc":"mp_f_stunt_01","component":11,"relative":3,"absolute":147,"texture":10,"palette":0},{"dlc":"mp_f_stunt_01","component":11,"relative":3,"absolute":147,"texture":10,"palette":1},{"dlc":"mp_f_stunt_01","component":11,"relative":3,"absolute":147,"texture":11,"palette":0},{"dlc":"mp_f_stunt_01","component":11,"relative":3,"absolute":147,"texture":11,"palette":1},{"dlc":"mp_f_stunt_01","component":11,"relative":4,"absolute":148,"texture":0,"palette":0},{"dlc":"mp_f_stunt_01","component":11,"relative":4,"absolute":148,"texture":0,"palette":1},{"dlc":"mp_f_stunt_01","component":11,"relative":4,"absolute":148,"texture":1,"palette":0},{"dlc":"mp_f_stunt_01","component":11,"relative":4,"absolute":148,"texture":1,"palette":1},{"dlc":"mp_f_stunt_01","component":11,"relative":4,"absolute":148,"texture":2,"palette":0},{"dlc":"mp_f_stunt_01","component":11,"relative":4,"absolute":148,"texture":2,"palette":1},{"dlc":"mp_f_stunt_01","component":11,"relative":4,"absolute":148,"texture":3,"palette":0},{"dlc":"mp_f_stunt_01","component":11,"relative":4,"absolute":148,"texture":3,"palette":1},{"dlc":"mp_f_stunt_01","component":11,"relative":4,"absolute":148,"texture":4,"palette":0},{"dlc":"mp_f_stunt_01","component":11,"relative":4,"absolute":148,"texture":4,"palette":1},{"dlc":"mp_f_stunt_01","component":11,"relative":4,"absolute":148,"texture":5,"palette":0},{"dlc":"mp_f_stunt_01","component":11,"relative":4,"absolute":148,"texture":5,"palette":1},{"dlc":"mp_f_stunt_01","component":11,"relative":5,"absolute":149,"texture":0,"palette":0},{"dlc":"mp_f_stunt_01","component":11,"relative":5,"absolute":149,"texture":0,"palette":1},{"dlc":"mp_f_stunt_01","component":11,"relative":5,"absolute":149,"texture":1,"palette":0},{"dlc":"mp_f_stunt_01","component":11,"relative":5,"absolute":149,"texture":1,"palette":1},{"dlc":"mp_f_stunt_01","component":11,"relative":5,"absolute":149,"texture":2,"palette":0},{"dlc":"mp_f_stunt_01","component":11,"relative":5,"absolute":149,"texture":2,"palette":1},{"dlc":"mp_f_stunt_01","component":11,"relative":5,"absolute":149,"texture":3,"palette":0},{"dlc":"mp_f_stunt_01","component":11,"relative":5,"absolute":149,"texture":3,"palette":1},{"dlc":"mp_f_stunt_01","component":11,"relative":5,"absolute":149,"texture":4,"palette":0},{"dlc":"mp_f_stunt_01","component":11,"relative":5,"absolute":149,"texture":4,"palette":1},{"dlc":"mp_f_stunt_01","component":11,"relative":5,"absolute":149,"texture":5,"palette":0},{"dlc":"mp_f_stunt_01","component":11,"relative":5,"absolute":149,"texture":5,"palette":1},{"dlc":"mp_f_stunt_01","component":11,"relative":5,"absolute":149,"texture":6,"palette":0},{"dlc":"mp_f_stunt_01","component":11,"relative":5,"absolute":149,"texture":6,"palette":1},{"dlc":"mp_f_stunt_01","component":11,"relative":5,"absolute":149,"texture":7,"palette":0},{"dlc":"mp_f_stunt_01","component":11,"relative":5,"absolute":149,"texture":7,"palette":1},{"dlc":"mp_f_stunt_01","component":11,"relative":5,"absolute":149,"texture":8,"palette":0},{"dlc":"mp_f_stunt_01","component":11,"relative":5,"absolute":149,"texture":8,"palette":1},{"dlc":"mp_f_stunt_01","component":11,"relative":5,"absolute":149,"texture":9,"palette":0},{"dlc":"mp_f_stunt_01","component":11,"relative":5,"absolute":149,"texture":9,"palette":1},{"dlc":"mp_f_stunt_01","component":11,"relative":5,"absolute":149,"texture":10,"palette":0},{"dlc":"mp_f_stunt_01","component":11,"relative":5,"absolute":149,"texture":10,"palette":1},{"dlc":"mp_f_stunt_01","component":11,"relative":5,"absolute":149,"texture":11,"palette":0},{"dlc":"mp_f_stunt_01","component":11,"relative":5,"absolute":149,"texture":11,"palette":1},{"dlc":"mp_f_stunt_01","component":11,"relative":5,"absolute":149,"texture":12,"palette":0},{"dlc":"mp_f_stunt_01","component":11,"relative":5,"absolute":149,"texture":12,"palette":1},{"dlc":"mp_f_stunt_01","component":11,"relative":5,"absolute":149,"texture":13,"palette":0},{"dlc":"mp_f_stunt_01","component":11,"relative":5,"absolute":149,"texture":13,"palette":1},{"dlc":"mp_f_stunt_01","component":11,"relative":5,"absolute":149,"texture":14,"palette":0},{"dlc":"mp_f_stunt_01","component":11,"relative":5,"absolute":149,"texture":14,"palette":1},{"dlc":"mp_f_stunt_01","component":11,"relative":5,"absolute":149,"texture":15,"palette":0},{"dlc":"mp_f_stunt_01","component":11,"relative":5,"absolute":149,"texture":15,"palette":1},{"dlc":"mp_f_stunt_01","component":11,"relative":6,"absolute":150,"texture":0,"palette":0},{"dlc":"mp_f_stunt_01","component":11,"relative":6,"absolute":150,"texture":0,"palette":1},{"dlc":"mp_f_stunt_01","component":11,"relative":6,"absolute":150,"texture":1,"palette":0},{"dlc":"mp_f_stunt_01","component":11,"relative":6,"absolute":150,"texture":1,"palette":1},{"dlc":"mp_f_stunt_01","component":11,"relative":6,"absolute":150,"texture":2,"palette":0},{"dlc":"mp_f_stunt_01","component":11,"relative":6,"absolute":150,"texture":2,"palette":1},{"dlc":"mp_f_stunt_01","component":11,"relative":6,"absolute":150,"texture":3,"palette":0},{"dlc":"mp_f_stunt_01","component":11,"relative":6,"absolute":150,"texture":3,"palette":1},{"dlc":"mp_f_stunt_01","component":11,"relative":6,"absolute":150,"texture":4,"palette":0},{"dlc":"mp_f_stunt_01","component":11,"relative":6,"absolute":150,"texture":4,"palette":1},{"dlc":"mp_f_stunt_01","component":11,"relative":6,"absolute":150,"texture":5,"palette":0},{"dlc":"mp_f_stunt_01","component":11,"relative":6,"absolute":150,"texture":5,"palette":1},{"dlc":"mp_f_stunt_01","component":11,"relative":6,"absolute":150,"texture":6,"palette":0},{"dlc":"mp_f_stunt_01","component":11,"relative":6,"absolute":150,"texture":6,"palette":1},{"dlc":"mp_f_stunt_01","component":11,"relative":6,"absolute":150,"texture":7,"palette":0},{"dlc":"mp_f_stunt_01","component":11,"relative":6,"absolute":150,"texture":7,"palette":1},{"dlc":"mp_f_stunt_01","component":11,"relative":6,"absolute":150,"texture":8,"palette":0},{"dlc":"mp_f_stunt_01","component":11,"relative":6,"absolute":150,"texture":8,"palette":1},{"dlc":"mp_f_stunt_01","component":11,"relative":6,"absolute":150,"texture":9,"palette":0},{"dlc":"mp_f_stunt_01","component":11,"relative":6,"absolute":150,"texture":9,"palette":1},{"dlc":"mp_f_stunt_01","component":11,"relative":6,"absolute":150,"texture":10,"palette":0},{"dlc":"mp_f_stunt_01","component":11,"relative":6,"absolute":150,"texture":10,"palette":1},{"dlc":"mp_f_stunt_01","component":11,"relative":6,"absolute":150,"texture":11,"palette":0},{"dlc":"mp_f_stunt_01","component":11,"relative":6,"absolute":150,"texture":11,"palette":1},{"dlc":"mp_f_stunt_01","component":11,"relative":6,"absolute":150,"texture":12,"palette":0},{"dlc":"mp_f_stunt_01","component":11,"relative":6,"absolute":150,"texture":12,"palette":1},{"dlc":"mp_f_stunt_01","component":11,"relative":6,"absolute":150,"texture":13,"palette":0},{"dlc":"mp_f_stunt_01","component":11,"relative":6,"absolute":150,"texture":13,"palette":1},{"dlc":"mp_f_stunt_01","component":11,"relative":6,"absolute":150,"texture":14,"palette":0},{"dlc":"mp_f_stunt_01","component":11,"relative":6,"absolute":150,"texture":14,"palette":1},{"dlc":"mp_f_stunt_01","component":11,"relative":6,"absolute":150,"texture":15,"palette":0},{"dlc":"mp_f_stunt_01","component":11,"relative":6,"absolute":150,"texture":15,"palette":1},{"dlc":"mp_f_stunt_01","component":11,"relative":6,"absolute":150,"texture":16,"palette":0},{"dlc":"mp_f_stunt_01","component":11,"relative":6,"absolute":150,"texture":16,"palette":1},{"dlc":"mp_f_stunt_01","component":11,"relative":6,"absolute":150,"texture":17,"palette":0},{"dlc":"mp_f_stunt_01","component":11,"relative":6,"absolute":150,"texture":17,"palette":1},{"dlc":"mp_f_stunt_01","component":11,"relative":6,"absolute":150,"texture":18,"palette":0},{"dlc":"mp_f_stunt_01","component":11,"relative":6,"absolute":150,"texture":18,"palette":1},{"dlc":"mp_f_stunt_01","component":11,"relative":6,"absolute":150,"texture":19,"palette":0},{"dlc":"mp_f_stunt_01","component":11,"relative":6,"absolute":150,"texture":19,"palette":1},{"dlc":"mp_f_stunt_01","component":11,"relative":6,"absolute":150,"texture":20,"palette":0},{"dlc":"mp_f_stunt_01","component":11,"relative":6,"absolute":150,"texture":20,"palette":1},{"dlc":"mp_f_stunt_01","component":11,"relative":6,"absolute":150,"texture":21,"palette":0},{"dlc":"mp_f_stunt_01","component":11,"relative":6,"absolute":150,"texture":21,"palette":1},{"dlc":"mp_f_stunt_01","component":11,"relative":6,"absolute":150,"texture":22,"palette":0},{"dlc":"mp_f_stunt_01","component":11,"relative":6,"absolute":150,"texture":22,"palette":1},{"dlc":"mp_f_stunt_01","component":11,"relative":6,"absolute":150,"texture":23,"palette":0},{"dlc":"mp_f_stunt_01","component":11,"relative":6,"absolute":150,"texture":23,"palette":1},{"dlc":"mp_f_stunt_01","component":11,"relative":6,"absolute":150,"texture":24,"palette":0},{"dlc":"mp_f_stunt_01","component":11,"relative":6,"absolute":150,"texture":24,"palette":1},{"dlc":"mp_f_stunt_01","component":11,"relative":6,"absolute":150,"texture":25,"palette":0},{"dlc":"mp_f_stunt_01","component":11,"relative":6,"absolute":150,"texture":25,"palette":1},{"dlc":"mp_f_stunt_01","component":11,"relative":7,"absolute":151,"texture":0,"palette":0},{"dlc":"mp_f_stunt_01","component":11,"relative":7,"absolute":151,"texture":0,"palette":1},{"dlc":"mp_f_stunt_01","component":11,"relative":7,"absolute":151,"texture":1,"palette":0},{"dlc":"mp_f_stunt_01","component":11,"relative":7,"absolute":151,"texture":1,"palette":1},{"dlc":"mp_f_stunt_01","component":11,"relative":7,"absolute":151,"texture":2,"palette":0},{"dlc":"mp_f_stunt_01","component":11,"relative":7,"absolute":151,"texture":2,"palette":1},{"dlc":"mp_f_stunt_01","component":11,"relative":7,"absolute":151,"texture":3,"palette":0},{"dlc":"mp_f_stunt_01","component":11,"relative":7,"absolute":151,"texture":3,"palette":1},{"dlc":"mp_f_stunt_01","component":11,"relative":7,"absolute":151,"texture":4,"palette":0},{"dlc":"mp_f_stunt_01","component":11,"relative":7,"absolute":151,"texture":4,"palette":1},{"dlc":"mp_f_stunt_01","component":11,"relative":7,"absolute":151,"texture":5,"palette":0},{"dlc":"mp_f_stunt_01","component":11,"relative":7,"absolute":151,"texture":5,"palette":1},{"dlc":"mp_f_stunt_01","component":11,"relative":7,"absolute":151,"texture":6,"palette":0},{"dlc":"mp_f_stunt_01","component":11,"relative":7,"absolute":151,"texture":6,"palette":1},{"dlc":"mp_f_stunt_01","component":11,"relative":7,"absolute":151,"texture":7,"palette":0},{"dlc":"mp_f_stunt_01","component":11,"relative":7,"absolute":151,"texture":7,"palette":1},{"dlc":"mp_f_stunt_01","component":11,"relative":8,"absolute":152,"texture":0,"palette":0},{"dlc":"mp_f_stunt_01","component":11,"relative":8,"absolute":152,"texture":0,"palette":1},{"dlc":"mp_f_stunt_01","component":11,"relative":8,"absolute":152,"texture":1,"palette":0},{"dlc":"mp_f_stunt_01","component":11,"relative":8,"absolute":152,"texture":1,"palette":1},{"dlc":"mp_f_stunt_01","component":11,"relative":8,"absolute":152,"texture":2,"palette":0},{"dlc":"mp_f_stunt_01","component":11,"relative":8,"absolute":152,"texture":2,"palette":1},{"dlc":"mp_f_stunt_01","component":11,"relative":8,"absolute":152,"texture":3,"palette":0},{"dlc":"mp_f_stunt_01","component":11,"relative":8,"absolute":152,"texture":3,"palette":1},{"dlc":"mp_f_stunt_01","component":11,"relative":9,"absolute":153,"texture":0,"palette":0},{"dlc":"mp_f_stunt_01","component":11,"relative":9,"absolute":153,"texture":0,"palette":1},{"dlc":"mp_f_stunt_01","component":11,"relative":9,"absolute":153,"texture":1,"palette":0},{"dlc":"mp_f_stunt_01","component":11,"relative":9,"absolute":153,"texture":1,"palette":1},{"dlc":"mp_f_stunt_01","component":11,"relative":9,"absolute":153,"texture":2,"palette":0},{"dlc":"mp_f_stunt_01","component":11,"relative":9,"absolute":153,"texture":2,"palette":1},{"dlc":"mp_f_stunt_01","component":11,"relative":9,"absolute":153,"texture":3,"palette":0},{"dlc":"mp_f_stunt_01","component":11,"relative":9,"absolute":153,"texture":3,"palette":1},{"dlc":"mp_f_stunt_01","component":11,"relative":9,"absolute":153,"texture":4,"palette":0},{"dlc":"mp_f_stunt_01","component":11,"relative":9,"absolute":153,"texture":4,"palette":1},{"dlc":"mp_f_stunt_01","component":11,"relative":9,"absolute":153,"texture":5,"palette":0},{"dlc":"mp_f_stunt_01","component":11,"relative":9,"absolute":153,"texture":5,"palette":1}]