[{"dlc":"mppilot","package":"Male_freemode_pilot","component":9,"relative":0,"absolute":11,"texture":0,"palette":0},{"dlc":"mppilot","package":"Male_freemode_pilot","component":9,"relative":0,"absolute":11,"texture":0,"palette":1},{"dlc":"mppilot","package":"Male_freemode_pilot","component":9,"relative":0,"absolute":11,"texture":1,"palette":0},{"dlc":"mppilot","package":"Male_freemode_pilot","component":9,"relative":0,"absolute":11,"texture":1,"palette":1},{"dlc":"mppilot","package":"Male_freemode_pilot","component":9,"relative":0,"absolute":11,"texture":2,"palette":0},{"dlc":"mppilot","package":"Male_freemode_pilot","component":9,"relative":0,"absolute":11,"texture":2,"palette":1},{"dlc":"mppilot","package":"Male_freemode_pilot","component":9,"relative":0,"absolute":11,"texture":3,"palette":0},{"dlc":"mppilot","package":"Male_freemode_pilot","component":9,"relative":0,"absolute":11,"texture":3,"palette":1},{"dlc":"mppilot","package":"Male_freemode_pilot","component":9,"relative":0,"absolute":11,"texture":4,"palette":0},{"dlc":"mppilot","package":"Male_freemode_pilot","component":9,"relative":0,"absolute":11,"texture":4,"palette":1}]