[{"dlc":"mp2023_01","package":"mp_m_2023_01","component":9,"relative":0,"absolute":57,"texture":0,"palette":0},{"dlc":"mp2023_01","package":"mp_m_2023_01","component":9,"relative":0,"absolute":57,"texture":0,"palette":1},{"dlc":"mp2023_01","package":"mp_m_2023_01","component":9,"relative":0,"absolute":57,"texture":1,"palette":0},{"dlc":"mp2023_01","package":"mp_m_2023_01","component":9,"relative":0,"absolute":57,"texture":1,"palette":1},{"dlc":"mp2023_01","package":"mp_m_2023_01","component":9,"relative":0,"absolute":57,"texture":2,"palette":0},{"dlc":"mp2023_01","package":"mp_m_2023_01","component":9,"relative":0,"absolute":57,"texture":2,"palette":1}]