[{"dlc":"mp2023_01","package":"mp_m_2023_01","component":7,"relative":0,"absolute":13,"texture":0,"palette":null},{"dlc":"mp2023_01","package":"mp_m_2023_01","component":7,"relative":0,"absolute":13,"texture":1,"palette":null},{"dlc":"mp2023_01","package":"mp_m_2023_01","component":7,"relative":0,"absolute":13,"texture":2,"palette":null},{"dlc":"mp2023_01","package":"mp_m_2023_01","component":7,"relative":0,"absolute":13,"texture":3,"palette":null},{"dlc":"mp2023_01","package":"mp_m_2023_01","component":7,"relative":0,"absolute":13,"texture":4,"palette":null},{"dlc":"mp2023_01","package":"mp_m_2023_01","component":7,"relative":0,"absolute":13,"texture":5,"palette":null}]