[{"dlc":"mpjanuary2016","package":"mp_f_January2016","component":2,"relative":0,"absolute":29,"texture":0,"palette":0},{"dlc":"mpjanuary2016","package":"mp_f_January2016","component":2,"relative":0,"absolute":29,"texture":0,"palette":1},{"dlc":"mpjanuary2016","package":"mp_f_January2016","component":2,"relative":1,"absolute":30,"texture":0,"palette":0},{"dlc":"mpjanuary2016","package":"mp_f_January2016","component":2,"relative":1,"absolute":30,"texture":0,"palette":1},{"dlc":"mpjanuary2016","package":"mp_f_January2016","component":2,"relative":2,"absolute":31,"texture":0,"palette":0},{"dlc":"mpjanuary2016","package":"mp_f_January2016","component":2,"relative":2,"absolute":31,"texture":0,"palette":1}]