[{"dlc":"mp_f_2024_01","component":11,"relative":0,"absolute":565,"texture":0,"palette":0},{"dlc":"mp_f_2024_01","component":11,"relative":0,"absolute":565,"texture":0,"palette":1},{"dlc":"mp_f_2024_01","component":11,"relative":0,"absolute":565,"texture":1,"palette":0},{"dlc":"mp_f_2024_01","component":11,"relative":0,"absolute":565,"texture":1,"palette":1},{"dlc":"mp_f_2024_01","component":11,"relative":0,"absolute":565,"texture":2,"palette":0},{"dlc":"mp_f_2024_01","component":11,"relative":0,"absolute":565,"texture":2,"palette":1},{"dlc":"mp_f_2024_01","component":11,"relative":0,"absolute":565,"texture":3,"palette":0},{"dlc":"mp_f_2024_01","component":11,"relative":0,"absolute":565,"texture":3,"palette":1},{"dlc":"mp_f_2024_01","component":11,"relative":0,"absolute":565,"texture":4,"palette":0},{"dlc":"mp_f_2024_01","component":11,"relative":0,"absolute":565,"texture":4,"palette":1},{"dlc":"mp_f_2024_01","component":11,"relative":0,"absolute":565,"texture":5,"palette":0},{"dlc":"mp_f_2024_01","component":11,"relative":0,"absolute":565,"texture":5,"palette":1},{"dlc":"mp_f_2024_01","component":11,"relative":0,"absolute":565,"texture":6,"palette":0},{"dlc":"mp_f_2024_01","component":11,"relative":0,"absolute":565,"texture":6,"palette":1},{"dlc":"mp_f_2024_01","component":11,"relative":0,"absolute":565,"texture":7,"palette":0},{"dlc":"mp_f_2024_01","component":11,"relative":0,"absolute":565,"texture":7,"palette":1},{"dlc":"mp_f_2024_01","component":11,"relative":0,"absolute":565,"texture":8,"palette":0},{"dlc":"mp_f_2024_01","component":11,"relative":0,"absolute":565,"texture":8,"palette":1},{"dlc":"mp_f_2024_01","component":11,"relative":0,"absolute":565,"texture":9,"palette":0},{"dlc":"mp_f_2024_01","component":11,"relative":0,"absolute":565,"texture":9,"palette":1},{"dlc":"mp_f_2024_01","component":11,"relative":0,"absolute":565,"texture":10,"palette":0},{"dlc":"mp_f_2024_01","component":11,"relative":0,"absolute":565,"texture":10,"palette":1},{"dlc":"mp_f_2024_01","component":11,"relative":0,"absolute":565,"texture":11,"palette":0},{"dlc":"mp_f_2024_01","component":11,"relative":0,"absolute":565,"texture":11,"palette":1},{"dlc":"mp_f_2024_01","component":11,"relative":0,"absolute":565,"texture":12,"palette":0},{"dlc":"mp_f_2024_01","component":11,"relative":0,"absolute":565,"texture":12,"palette":1},{"dlc":"mp_f_2024_01","component":11,"relative":0,"absolute":565,"texture":13,"palette":0},{"dlc":"mp_f_2024_01","component":11,"relative":0,"absolute":565,"texture":13,"palette":1},{"dlc":"mp_f_2024_01","component":11,"relative":0,"absolute":565,"texture":14,"palette":0},{"dlc":"mp_f_2024_01","component":11,"relative":0,"absolute":565,"texture":14,"palette":1},{"dlc":"mp_f_2024_01","component":11,"relative":0,"absolute":565,"texture":15,"palette":0},{"dlc":"mp_f_2024_01","component":11,"relative":0,"absolute":565,"texture":15,"palette":1},{"dlc":"mp_f_2024_01","component":11,"relative":0,"absolute":565,"texture":16,"palette":0},{"dlc":"mp_f_2024_01","component":11,"relative":0,"absolute":565,"texture":16,"palette":1},{"dlc":"mp_f_2024_01","component":11,"relative":0,"absolute":565,"texture":17,"palette":0},{"dlc":"mp_f_2024_01","component":11,"relative":0,"absolute":565,"texture":17,"palette":1},{"dlc":"mp_f_2024_01","component":11,"relative":0,"absolute":565,"texture":18,"palette":0},{"dlc":"mp_f_2024_01","component":11,"relative":0,"absolute":565,"texture":18,"palette":1},{"dlc":"mp_f_2024_01","component":11,"relative":0,"absolute":565,"texture":19,"palette":0},{"dlc":"mp_f_2024_01","component":11,"relative":0,"absolute":565,"texture":19,"palette":1},{"dlc":"mp_f_2024_01","component":11,"relative":0,"absolute":565,"texture":20,"palette":0},{"dlc":"mp_f_2024_01","component":11,"relative":0,"absolute":565,"texture":20,"palette":1},{"dlc":"mp_f_2024_01","component":11,"relative":0,"absolute":565,"texture":21,"palette":0},{"dlc":"mp_f_2024_01","component":11,"relative":0,"absolute":565,"texture":21,"palette":1},{"dlc":"mp_f_2024_01","component":11,"relative":0,"absolute":565,"texture":22,"palette":0},{"dlc":"mp_f_2024_01","component":11,"relative":0,"absolute":565,"texture":22,"palette":1},{"dlc":"mp_f_2024_01","component":11,"relative":0,"absolute":565,"texture":23,"palette":0},{"dlc":"mp_f_2024_01","component":11,"relative":0,"absolute":565,"texture":23,"palette":1},{"dlc":"mp_f_2024_01","component":11,"relative":0,"absolute":565,"texture":24,"palette":0},{"dlc":"mp_f_2024_01","component":11,"relative":0,"absolute":565,"texture":24,"palette":1},{"dlc":"mp_f_2024_01","component":11,"relative":0,"absolute":565,"texture":25,"palette":0},{"dlc":"mp_f_2024_01","component":11,"relative":0,"absolute":565,"texture":25,"palette":1},{"dlc":"mp_f_2024_01","component":11,"relative":1,"absolute":566,"texture":0,"palette":0},{"dlc":"mp_f_2024_01","component":11,"relative":1,"absolute":566,"texture":0,"palette":1},{"dlc":"mp_f_2024_01","component":11,"relative":1,"absolute":566,"texture":1,"palette":0},{"dlc":"mp_f_2024_01","component":11,"relative":1,"absolute":566,"texture":1,"palette":1},{"dlc":"mp_f_2024_01","component":11,"relative":1,"absolute":566,"texture":2,"palette":0},{"dlc":"mp_f_2024_01","component":11,"relative":1,"absolute":566,"texture":2,"palette":1},{"dlc":"mp_f_2024_01","component":11,"relative":1,"absolute":566,"texture":3,"palette":0},{"dlc":"mp_f_2024_01","component":11,"relative":1,"absolute":566,"texture":3,"palette":1},{"dlc":"mp_f_2024_01","component":11,"relative":1,"absolute":566,"texture":4,"palette":0},{"dlc":"mp_f_2024_01","component":11,"relative":1,"absolute":566,"texture":4,"palette":1},{"dlc":"mp_f_2024_01","component":11,"relative":1,"absolute":566,"texture":5,"palette":0},{"dlc":"mp_f_2024_01","component":11,"relative":1,"absolute":566,"texture":5,"palette":1},{"dlc":"mp_f_2024_01","component":11,"relative":1,"absolute":566,"texture":6,"palette":0},{"dlc":"mp_f_2024_01","component":11,"relative":1,"absolute":566,"texture":6,"palette":1},{"dlc":"mp_f_2024_01","component":11,"relative":1,"absolute":566,"texture":7,"palette":0},{"dlc":"mp_f_2024_01","component":11,"relative":1,"absolute":566,"texture":7,"palette":1},{"dlc":"mp_f_2024_01","component":11,"relative":1,"absolute":566,"texture":8,"palette":0},{"dlc":"mp_f_2024_01","component":11,"relative":1,"absolute":566,"texture":8,"palette":1},{"dlc":"mp_f_2024_01","component":11,"relative":1,"absolute":566,"texture":9,"palette":0},{"dlc":"mp_f_2024_01","component":11,"relative":1,"absolute":566,"texture":9,"palette":1},{"dlc":"mp_f_2024_01","component":11,"relative":1,"absolute":566,"texture":10,"palette":0},{"dlc":"mp_f_2024_01","component":11,"relative":1,"absolute":566,"texture":10,"palette":1},{"dlc":"mp_f_2024_01","component":11,"relative":1,"absolute":566,"texture":11,"palette":0},{"dlc":"mp_f_2024_01","component":11,"relative":1,"absolute":566,"texture":11,"palette":1},{"dlc":"mp_f_2024_01","component":11,"relative":1,"absolute":566,"texture":12,"palette":0},{"dlc":"mp_f_2024_01","component":11,"relative":1,"absolute":566,"texture":12,"palette":1},{"dlc":"mp_f_2024_01","component":11,"relative":1,"absolute":566,"texture":13,"palette":0},{"dlc":"mp_f_2024_01","component":11,"relative":1,"absolute":566,"texture":13,"palette":1},{"dlc":"mp_f_2024_01","component":11,"relative":2,"absolute":567,"texture":0,"palette":0},{"dlc":"mp_f_2024_01","component":11,"relative":2,"absolute":567,"texture":0,"palette":1},{"dlc":"mp_f_2024_01","component":11,"relative":3,"absolute":568,"texture":0,"palette":0},{"dlc":"mp_f_2024_01","component":11,"relative":3,"absolute":568,"texture":0,"palette":1},{"dlc":"mp_f_2024_01","component":11,"relative":4,"absolute":569,"texture":0,"palette":0},{"dlc":"mp_f_2024_01","component":11,"relative":4,"absolute":569,"texture":0,"palette":1},{"dlc":"mp_f_2024_01","component":11,"relative":5,"absolute":570,"texture":0,"palette":0},{"dlc":"mp_f_2024_01","component":11,"relative":5,"absolute":570,"texture":0,"palette":1},{"dlc":"mp_f_2024_01","component":11,"relative":6,"absolute":571,"texture":0,"palette":0},{"dlc":"mp_f_2024_01","component":11,"relative":6,"absolute":571,"texture":0,"palette":1},{"dlc":"mp_f_2024_01","component":11,"relative":7,"absolute":572,"texture":0,"palette":0},{"dlc":"mp_f_2024_01","component":11,"relative":7,"absolute":572,"texture":0,"palette":1},{"dlc":"mp_f_2024_01","component":11,"relative":8,"absolute":573,"texture":0,"palette":0},{"dlc":"mp_f_2024_01","component":11,"relative":8,"absolute":573,"texture":0,"palette":1},{"dlc":"mp_f_2024_01","component":11,"relative":8,"absolute":573,"texture":1,"palette":0},{"dlc":"mp_f_2024_01","component":11,"relative":8,"absolute":573,"texture":1,"palette":1},{"dlc":"mp_f_2024_01","component":11,"relative":8,"absolute":573,"texture":2,"palette":0},{"dlc":"mp_f_2024_01","component":11,"relative":8,"absolute":573,"texture":2,"palette":1},{"dlc":"mp_f_2024_01","component":11,"relative":8,"absolute":573,"texture":3,"palette":0},{"dlc":"mp_f_2024_01","component":11,"relative":8,"absolute":573,"texture":3,"palette":1},{"dlc":"mp_f_2024_01","component":11,"relative":8,"absolute":573,"texture":4,"palette":0},{"dlc":"mp_f_2024_01","component":11,"relative":8,"absolute":573,"texture":4,"palette":1},{"dlc":"mp_f_2024_01","component":11,"relative":8,"absolute":573,"texture":5,"palette":0},{"dlc":"mp_f_2024_01","component":11,"relative":8,"absolute":573,"texture":5,"palette":1},{"dlc":"mp_f_2024_01","component":11,"relative":8,"absolute":573,"texture":6,"palette":0},{"dlc":"mp_f_2024_01","component":11,"relative":8,"absolute":573,"texture":6,"palette":1},{"dlc":"mp_f_2024_01","component":11,"relative":8,"absolute":573,"texture":7,"palette":0},{"dlc":"mp_f_2024_01","component":11,"relative":8,"absolute":573,"texture":7,"palette":1},{"dlc":"mp_f_2024_01","component":11,"relative":8,"absolute":573,"texture":8,"palette":0},{"dlc":"mp_f_2024_01","component":11,"relative":8,"absolute":573,"texture":8,"palette":1},{"dlc":"mp_f_2024_01","component":11,"relative":8,"absolute":573,"texture":9,"palette":0},{"dlc":"mp_f_2024_01","component":11,"relative":8,"absolute":573,"texture":9,"palette":1},{"dlc":"mp_f_2024_01","component":11,"relative":8,"absolute":573,"texture":10,"palette":0},{"dlc":"mp_f_2024_01","component":11,"relative":8,"absolute":573,"texture":10,"palette":1},{"dlc":"mp_f_2024_01","component":11,"relative":8,"absolute":573,"texture":11,"palette":0},{"dlc":"mp_f_2024_01","component":11,"relative":8,"absolute":573,"texture":11,"palette":1},{"dlc":"mp_f_2024_01","component":11,"relative":8,"absolute":573,"texture":12,"palette":0},{"dlc":"mp_f_2024_01","component":11,"relative":8,"absolute":573,"texture":12,"palette":1},{"dlc":"mp_f_2024_01","component":11,"relative":8,"absolute":573,"texture":13,"palette":0},{"dlc":"mp_f_2024_01","component":11,"relative":8,"absolute":573,"texture":13,"palette":1},{"dlc":"mp_f_2024_01","component":11,"relative":8,"absolute":573,"texture":14,"palette":0},{"dlc":"mp_f_2024_01","component":11,"relative":8,"absolute":573,"texture":14,"palette":1},{"dlc":"mp_f_2024_01","component":11,"relative":8,"absolute":573,"texture":15,"palette":0},{"dlc":"mp_f_2024_01","component":11,"relative":8,"absolute":573,"texture":15,"palette":1},{"dlc":"mp_f_2024_01","component":11,"relative":8,"absolute":573,"texture":16,"palette":0},{"dlc":"mp_f_2024_01","component":11,"relative":8,"absolute":573,"texture":16,"palette":1},{"dlc":"mp_f_2024_01","component":11,"relative":8,"absolute":573,"texture":17,"palette":0},{"dlc":"mp_f_2024_01","component":11,"relative":8,"absolute":573,"texture":17,"palette":1},{"dlc":"mp_f_2024_01","component":11,"relative":8,"absolute":573,"texture":18,"palette":0},{"dlc":"mp_f_2024_01","component":11,"relative":8,"absolute":573,"texture":18,"palette":1},{"dlc":"mp_f_2024_01","component":11,"relative":8,"absolute":573,"texture":19,"palette":0},{"dlc":"mp_f_2024_01","component":11,"relative":8,"absolute":573,"texture":19,"palette":1},{"dlc":"mp_f_2024_01","component":11,"relative":8,"absolute":573,"texture":20,"palette":0},{"dlc":"mp_f_2024_01","component":11,"relative":8,"absolute":573,"texture":20,"palette":1},{"dlc":"mp_f_2024_01","component":11,"relative":8,"absolute":573,"texture":21,"palette":0},{"dlc":"mp_f_2024_01","component":11,"relative":8,"absolute":573,"texture":21,"palette":1},{"dlc":"mp_f_2024_01","component":11,"relative":8,"absolute":573,"texture":22,"palette":0},{"dlc":"mp_f_2024_01","component":11,"relative":8,"absolute":573,"texture":22,"palette":1},{"dlc":"mp_f_2024_01","component":11,"relative":8,"absolute":573,"texture":23,"palette":0},{"dlc":"mp_f_2024_01","component":11,"relative":8,"absolute":573,"texture":23,"palette":1},{"dlc":"mp_f_2024_01","component":11,"relative":8,"absolute":573,"texture":24,"palette":0},{"dlc":"mp_f_2024_01","component":11,"relative":8,"absolute":573,"texture":24,"palette":1},{"dlc":"mp_f_2024_01","component":11,"relative":8,"absolute":573,"texture":25,"palette":0},{"dlc":"mp_f_2024_01","component":11,"relative":8,"absolute":573,"texture":25,"palette":1},{"dlc":"mp_f_2024_01","component":11,"relative":9,"absolute":574,"texture":0,"palette":0},{"dlc":"mp_f_2024_01","component":11,"relative":9,"absolute":574,"texture":0,"palette":1},{"dlc":"mp_f_2024_01","component":11,"relative":9,"absolute":574,"texture":1,"palette":0},{"dlc":"mp_f_2024_01","component":11,"relative":9,"absolute":574,"texture":1,"palette":1},{"dlc":"mp_f_2024_01","component":11,"relative":12,"absolute":577,"texture":0,"palette":0},{"dlc":"mp_f_2024_01","component":11,"relative":12,"absolute":577,"texture":0,"palette":1},{"dlc":"mp_f_2024_01","component":11,"relative":15,"absolute":580,"texture":0,"palette":0},{"dlc":"mp_f_2024_01","component":11,"relative":15,"absolute":580,"texture":0,"palette":1},{"dlc":"mp_f_2024_01","component":11,"relative":16,"absolute":581,"texture":0,"palette":0},{"dlc":"mp_f_2024_01","component":11,"relative":16,"absolute":581,"texture":0,"palette":1},{"dlc":"mp_f_2024_01","component":11,"relative":16,"absolute":581,"texture":1,"palette":0},{"dlc":"mp_f_2024_01","component":11,"relative":16,"absolute":581,"texture":1,"palette":1},{"dlc":"mp_f_2024_01","component":11,"relative":17,"absolute":582,"texture":0,"palette":0},{"dlc":"mp_f_2024_01","component":11,"relative":17,"absolute":582,"texture":0,"palette":1},{"dlc":"mp_f_2024_01","component":11,"relative":17,"absolute":582,"texture":1,"palette":0},{"dlc":"mp_f_2024_01","component":11,"relative":17,"absolute":582,"texture":1,"palette":1},{"dlc":"mp_f_2024_01","component":11,"relative":17,"absolute":582,"texture":2,"palette":0},{"dlc":"mp_f_2024_01","component":11,"relative":17,"absolute":582,"texture":2,"palette":1},{"dlc":"mp_f_2024_01","component":11,"relative":18,"absolute":583,"texture":0,"palette":0},{"dlc":"mp_f_2024_01","component":11,"relative":18,"absolute":583,"texture":0,"palette":1},{"dlc":"mp_f_2024_01","component":11,"relative":18,"absolute":583,"texture":1,"palette":0},{"dlc":"mp_f_2024_01","component":11,"relative":18,"absolute":583,"texture":1,"palette":1},{"dlc":"mp_f_2024_01","component":11,"relative":18,"absolute":583,"texture":2,"palette":0},{"dlc":"mp_f_2024_01","component":11,"relative":18,"absolute":583,"texture":2,"palette":1},{"dlc":"mp_f_2024_01","component":11,"relative":18,"absolute":583,"texture":3,"palette":0},{"dlc":"mp_f_2024_01","component":11,"relative":18,"absolute":583,"texture":3,"palette":1},{"dlc":"mp_f_2024_01","component":11,"relative":18,"absolute":583,"texture":4,"palette":0},{"dlc":"mp_f_2024_01","component":11,"relative":18,"absolute":583,"texture":4,"palette":1},{"dlc":"mp_f_2024_01","component":11,"relative":18,"absolute":583,"texture":5,"palette":0},{"dlc":"mp_f_2024_01","component":11,"relative":18,"absolute":583,"texture":5,"palette":1},{"dlc":"mp_f_2024_01","component":11,"relative":18,"absolute":583,"texture":6,"palette":0},{"dlc":"mp_f_2024_01","component":11,"relative":18,"absolute":583,"texture":6,"palette":1},{"dlc":"mp_f_2024_01","component":11,"relative":18,"absolute":583,"texture":7,"palette":0},{"dlc":"mp_f_2024_01","component":11,"relative":18,"absolute":583,"texture":7,"palette":1},{"dlc":"mp_f_2024_01","component":11,"relative":18,"absolute":583,"texture":8,"palette":0},{"dlc":"mp_f_2024_01","component":11,"relative":18,"absolute":583,"texture":8,"palette":1},{"dlc":"mp_f_2024_01","component":11,"relative":18,"absolute":583,"texture":9,"palette":0},{"dlc":"mp_f_2024_01","component":11,"relative":18,"absolute":583,"texture":9,"palette":1},{"dlc":"mp_f_2024_01","component":11,"relative":18,"absolute":583,"texture":10,"palette":0},{"dlc":"mp_f_2024_01","component":11,"relative":18,"absolute":583,"texture":10,"palette":1},{"dlc":"mp_f_2024_01","component":11,"relative":18,"absolute":583,"texture":11,"palette":0},{"dlc":"mp_f_2024_01","component":11,"relative":18,"absolute":583,"texture":11,"palette":1},{"dlc":"mp_f_2024_01","component":11,"relative":18,"absolute":583,"texture":12,"palette":0},{"dlc":"mp_f_2024_01","component":11,"relative":18,"absolute":583,"texture":12,"palette":1},{"dlc":"mp_f_2024_01","component":11,"relative":18,"absolute":583,"texture":13,"palette":0},{"dlc":"mp_f_2024_01","component":11,"relative":18,"absolute":583,"texture":13,"palette":1},{"dlc":"mp_f_2024_01","component":11,"relative":18,"absolute":583,"texture":14,"palette":0},{"dlc":"mp_f_2024_01","component":11,"relative":18,"absolute":583,"texture":14,"palette":1}]