[{"dlc":"patchday1ng","position":{"x":1721.0479,"y":3279.3872,"z":40.701862},"relative":0,"absolute":null,"name":"airfield"},{"dlc":"patchday1ng","position":{"x":2017.2471,"y":3829.5518,"z":31.764627},"relative":1,"absolute":null,"name":"cs4_04_trash"},{"dlc":"patchday1ng","position":{"x":1586.6414,"y":3825.7588,"z":37.848953},"relative":2,"absolute":null,"name":"cs4_04_triaf03"},{"dlc":"patchday1ng","position":{"x":1757.8389,"y":3899.8657,"z":40.94342},"relative":3,"absolute":null,"name":"cs4_08_triaf02"},{"dlc":"patchday1ng","position":{"x":2087.5825,"y":3154.9617,"z":49.260967},"relative":4,"absolute":null,"name":"racetrack01"},{"dlc":"patchday1ng","position":{"x":1855.8372,"y":3683.9902,"z":34.597248},"relative":5,"absolute":null,"name":"sheriff_cap"},{"dlc":"patchday1ng","position":{"x":-164.87866,"y":-2365.9558,"z":12.266846},"relative":6,"absolute":null,"name":"ship_occ_grp1"},{"dlc":"patchday1ng","position":{"x":-164.87866,"y":-2345.0696,"z":-1.3571777},"relative":7,"absolute":null,"name":"ship_occ_grp2"},{"dlc":"patchday1ng","position":{"x":1974.4581,"y":3819.1328,"z":33.938362},"relative":8,"absolute":null,"name":"trevorsmp"},{"dlc":"patchday1ng","mlo":"v_trailer","position":{"x":1973.3025,"y":3818.5088,"z":33.91721},"relative":9,"absolute":null,"name":"trevorstrailer"},{"dlc":"patchday1ng","position":{"x":1974.1147,"y":3813.7163,"z":28.825932},"relative":10,"absolute":null,"name":"trevorstrailercollision"},{"dlc":"patchday1ng","mlo":"v_trailertidy","position":{"x":1973.3025,"y":3818.5088,"z":33.91721},"relative":11,"absolute":null,"name":"trevorstrailertidy"},{"dlc":"patchday1ng","mlo":"v_trailertrash","position":{"x":1973.3025,"y":3818.5088,"z":33.91721},"relative":12,"absolute":null,"name":"trevorstrailertrash"}]